adafruit_circuitpython_rgb_display-3.14.3.dist-info/licenses/LICENSE
adafruit_rgb_display/__init__.py
adafruit_rgb_display/gc9a01a.py
adafruit_rgb_display/hx8353.py
adafruit_rgb_display/hx8357.py
adafruit_rgb_display/ili9341.py
adafruit_rgb_display/rgb.py
adafruit_rgb_display/s6d02a1.py
adafruit_rgb_display/ssd1331.py
adafruit_rgb_display/ssd1351.py
adafruit_rgb_display/st7735.py
adafruit_rgb_display/st7789.py
adafruit_circuitpython_rgb_display-3.14.3.dist-info/METADATA
adafruit_circuitpython_rgb_display-3.14.3.dist-info/WHEEL
adafruit_circuitpython_rgb_display-3.14.3.dist-info/top_level.txt
adafruit_circuitpython_rgb_display-3.14.3.dist-info/RECORD
